mongocat/__init__.py
mongocat/cli.py
mongocat/mongocat.py
mongocat-0.2.1.dist-info/AUTHORS.rst
mongocat-0.2.1.dist-info/LICENSE
mongocat-0.2.1.dist-info/METADATA
mongocat-0.2.1.dist-info/WHEEL
mongocat-0.2.1.dist-info/entry_points.txt
mongocat-0.2.1.dist-info/top_level.txt
mongocat-0.2.1.dist-info/RECORD
