Metadata-Version: 2.1
Name: mongocat
Version: 0.2.1
Summary: Cli tool to interact with mongodb
Home-page: https://github.com/DaniloZZZ/mongocat
Author: Danylo Lykov
Author-email: lkvdan@gmail.com
License: MIT license
Keywords: mongocat
Platform: UNKNOWN
Classifier: Development Status :: 2 - Pre-Alpha
Classifier: Intended Audience :: Developers
Classifier: License :: OSI Approved :: MIT License
Classifier: Natural Language :: English
Classifier: Programming Language :: Python :: 3
Classifier: Programming Language :: Python :: 3.5
Classifier: Programming Language :: Python :: 3.6
Classifier: Programming Language :: Python :: 3.7
Classifier: Programming Language :: Python :: 3.8
Requires-Python: >=3.5
Requires-Dist: Click (>=7.0)
Requires-Dist: pymongo
Requires-Dist: dnspython
Requires-Dist: pyyaml
